uart_rx.v
module uart_rx (
    input clk, rst, Rx_Serial,
    input [3:0] clk_div,
    output reg Rx_Data    
);

    parameter s_Idle = 2'b00, s_Start = 2'b01, s_Read = 2'b10, s_Stop = 2'b11;
    reg [2:0] state = 'b0;
    reg [2:0] bit_indx;
    reg [3:0] count;

    reg mem [0:7];

    always @(posedge clk or negedge rst) begin
        if (~rst) begin
            state <= s_Idle;
            bit_indx <= 'b0;
            count <= 'b0;
            Rx_Data <= 1'b1;
        end

        else begin
            case (state)
                s_Idle:
                begin
                    bit_indx  <= 'b0;
                    count <= 'b0;
                    if(Rx_Serial == 1'b0) begin                    
                        state <= s_Start;
                    end 
                    else begin
                        state <= s_Idle;
                    end              
                end

                s_Start:
                begin
                    count <= count + 1'b1;
                    if(count == (clk_div/2 - 1'b1)) begin
                        if (Rx_Serial == 1'b0)
                            state <= s_Read;
                        else
                            state <= s_Idle;
                    end
                    else 
                        state <= s_Start;
                end

                s_Read: begin
                    count <= count + 1'b1;
                    mem [bit_indx] <= Rx_Serial;
                    if (count == clk_div - 1'b1) begin
                        count <= 'b0;
                        if (bit_indx < 3'b111) begin
                            Rx_Data <= Rx_Serial;
                            bit_indx <= bit_indx + 1'b1;
                            state <= s_Read;
                        end
                        else begin
                            state <= s_Stop;
                        end
                    end
                    else
                        state <= s_Read;

                end

                s_Stop: state <= s_Idle;
            endcase
        end      
    end
endmodule //uart_rx

// module tb;

//     reg clk, rx_Serial;
//     wire [7:0] Rx_Data;

//     reg [7:0] data;
//     reg[3:0] count;

//     reg rst;
//     reg [10:0] dvsr;
//     wire tick;
    
//     baud_gen bdclk(clk, rst, dvsr, tick);
//     uart_rx uut(tick, rx_Serial, Rx_Data);

//     initial begin
//         clk         = 1'b1;
//         data        = 8'b11010111;
//         count       = 'b0;
//         dvsr        = 10;
//         rx_Serial   = 1'b1;
//         rst         = 1'b1;
//         #2 rst      = ~rst;

//         #(100*dvsr)  @(negedge tick) rx_Serial = 1'b0;

//         while(count <= 8) @(negedge tick)begin
//             rx_Serial   = data[count];
//             count       = count + 1;
//         end

//         rx_Serial <= 1'b1;
//         #(100*dvsr); 
//         $display("Rx_data = %b", Rx_Data);
         
//         $finish;
//     end

//     always #5 clk = ~clk;

//     initial begin
//         $dumpfile("reciever.vcd");
//         $dumpvars(0, tb);
//     end
// endmodule //uart_rx_tb

uart_tx.v
module uart_tx (
    input clk, Tx_Drive,
    input [3:0] clk_div,
    input rst,
    output reg Tx_Serial, Tx_Active    
);

    reg [3:0] count;
    reg [2:0] bit_indx;

    reg mem [0:7];
    initial $readmemb("data_memory.bin", mem);

    parameter s_IDLE = 3'b000, s_START = 3'b001, s_DATA = 3'b010, s_STOP = 3'b011;
    reg [2:0] state = 3'b000;

    always @(posedge clk or negedge rst) begin
        if(!rst) begin
            state <= s_IDLE;
            count <= 'b0;
            Tx_Serial <= 1'b1;
            Tx_Active <= 1'b0;
            bit_indx <= 'b0;
        end
        else begin 
            case (state)
            s_IDLE: begin
                count <= 'b0;
                Tx_Serial <= 1'b1;
                Tx_Active <= 1'b0;
                
                if(!Tx_Drive | (Tx_Drive & bit_indx == 'b1)) 
                    state <= s_IDLE;
                else 
                    state <= s_START;
                
            end

            s_START: begin
                count <= count + 1'b1;
                Tx_Serial <= 1'b0;
                if (count == clk_div - 1'b1) begin
                    state <= s_DATA;
                    count <= 'b0;
                    bit_indx <= 3'b000;
                    Tx_Active <= 1'b1;
                end
                else 
                    state <= s_START;
            end

            s_DATA: begin
                count <= count + 1'b1;
                Tx_Serial <= mem[bit_indx];
                
                if (count == clk_div - 1'b1) begin
                    count <= 'b0;
                    if (bit_indx < 3'b111) begin
                        bit_indx <= bit_indx + 1'b1;
                        state <= s_DATA;
                    end else begin
                        state <= s_STOP;
                    end
                end
            end


            s_STOP: begin
                if (count == clk_div - 'b1) begin
                    Tx_Serial <= 1'b1;
                    Tx_Active <= 1'b0;
                    state <= s_IDLE;
                end
            end

            default: begin
                state <= s_IDLE;
            end
            endcase
        end
    end
endmodule //uart_tx

// module tb;
//     reg clk, Tx_Drive;
//     reg rst;
//     reg [3:0] dvsr;
    
//     wire Tx_Serial, Tx_Active;

//     uart_tx uut (clk, Tx_Drive, dvsr, rst, Tx_Serial, Tx_Active);

//     initial begin
//         clk     = 1;        
//         Tx_Drive = 0;
//         rst     = 1;
//         dvsr    = 10;
//         #2 rst  = ~rst;
//         #2 rst  = ~rst;

//         #100 Tx_Drive = 1'b1;

//         #(dvsr * 100) 
//         // for (integer i = 0; i<= 7; i = i+1) begin
//         //     $display("%b", uut.mem[i]);
//         // end
//         $finish;
//     end

//     always #5 clk = !clk;

//     initial begin
//         $monitor(Tx_Serial);
//     end

//     initial begin
//         $dumpfile("dump.vcd");
//         $dumpvars(0, tb);
//     end
    
// endmodule // uart_tx_tb

Top_Module.v
`include "uart_tx.v"
`include "uart_rx.v"

module Top_Module (clk_tx, clk_rx, rst, clk_div_tx, clk_div_rx, Tx_Drive);

    input clk_tx, clk_rx, rst, Tx_Drive;
    input [3:0] clk_div_tx, clk_div_rx;

    wire Rx_Data, Tx_Serial, Tx_Active;
 
    uart_tx uart_tx (.clk(clk_tx), .Tx_Drive(Tx_Drive), .clk_div(clk_div_tx), .rst(rst), .Tx_Serial(Tx_Serial), .Tx_Active(Tx_Active));

    uart_rx uart_rx(.clk(clk_rx), .rst(rst), .Rx_Serial(Tx_Serial), .clk_div(clk_div_rx), .Rx_Data(Rx_Data));

endmodule

tb.v
`include "Top_Module.v"

// Set Parameter CLKS_PER_BIT as follows:
// clk_div = (Frequency of i_Clock)/(Frequency of UART)
// Example: 10 MHz Clock, 115200 baud UART
// (10000000)/(115200) = 87
module tb;

    reg clk_tx, clk_rx, rst, Tx_Drive;
    reg [3:0] clk_div_tx;
    reg [3:0] clk_div_rx;

    Top_Module Top_Module(.clk_tx(clk_tx), .clk_rx(clk_rx), .rst(rst), .clk_div_tx(clk_div_tx), .clk_div_rx(clk_div_rx), .Tx_Drive(Tx_Drive));

    always #5 clk_tx = ~clk_tx;
    always #5 clk_rx = ~clk_rx;

    initial begin
        clk_tx = 1'b0;
        clk_rx = 1'b0;
        rst = 1'b1;
        Tx_Drive = 1'b0;
        clk_div_tx = 4'd2;
        clk_div_rx = 4'd2;

        #2 rst = ~rst;
        #2 rst = ~rst;

        #(clk_div_tx * 10) Tx_Drive = 1'b1;

        #(200 * clk_div_tx) 
        for (integer i = 0; i <= 7; i = i+1) begin
            $display("%b", Top_Module.uart_rx.mem[i]);
        end
        $finish;
    end

    initial begin
        $dumpfile("dump.vcd");
        $dumpvars(0, tb);
    end

endmodule


// module tb;
//     reg clk, Tx_Drive;
//     reg rst;
//     reg [3:0] dvsr;
    
//     wire Tx_Serial, Tx_Active;

//     uart_tx uut (clk, Tx_Drive, dvsr, rst, Tx_Serial, Tx_Active);

//     initial begin
//         clk     = 1;        
//         Tx_Drive = 0;
//         rst     = 1;
//         dvsr    = 10;
//         #2 rst  = ~rst;
//         #2 rst  = ~rst;

//         #100 Tx_Drive = 1'b1;

//         #(dvsr * 100) 
//         // for (integer i = 0; i<= 7; i = i+1) begin
//         //     $display("%b", uut.mem[i]);
//         // end
//         $finish;
//     end

//     always #5 clk = !clk;

//     initial begin
//         $monitor(Tx_Serial);
//     end

    // initial begin
    //     $dumpfile("dump.vcd");
    //     $dumpvars(0, tb);
    // end
    
// endmodule // uart_tx_tb

dump.vcd
$date
	Sun Aug 24 04:34:53 2025
$end
$version
	Icarus Verilog
$end
$timescale
	1s
$end
$scope module tb $end
$var reg 1 ! Tx_Drive $end
$var reg 4 " clk_div_rx [3:0] $end
$var reg 4 # clk_div_tx [3:0] $end
$var reg 1 $ clk_rx $end
$var reg 1 % clk_tx $end
$var reg 1 & rst $end
$scope module Top_Module $end
$var wire 1 ! Tx_Drive $end
$var wire 4 ' clk_div_rx [3:0] $end
$var wire 4 ( clk_div_tx [3:0] $end
$var wire 1 $ clk_rx $end
$var wire 1 % clk_tx $end
$var wire 1 & rst $end
$var wire 1 ) Tx_Serial $end
$var wire 1 * Tx_Active $end
$var wire 1 + Rx_Data $end
$scope module uart_rx $end
$var wire 1 $ clk $end
$var wire 4 , clk_div [3:0] $end
$var wire 1 & rst $end
$var wire 1 ) Rx_Serial $end
$var parameter 2 - s_Idle $end
$var parameter 2 . s_Read $end
$var parameter 2 / s_Start $end
$var parameter 2 0 s_Stop $end
$var reg 1 + Rx_Data $end
$var reg 3 1 bit_indx [2:0] $end
$var reg 4 2 count [3:0] $end
$var reg 3 3 state [2:0] $end
$upscope $end
$scope module uart_tx $end
$var wire 1 ! Tx_Drive $end
$var wire 1 % clk $end
$var wire 4 4 clk_div [3:0] $end
$var wire 1 & rst $end
$var parameter 3 5 s_DATA $end
$var parameter 3 6 s_IDLE $end
$var parameter 3 7 s_START $end
$var parameter 3 8 s_STOP $end
$var reg 1 * Tx_Active $end
$var reg 1 ) Tx_Serial $end
$var reg 3 9 bit_indx [2:0] $end
$var reg 4 : count [3:0] $end
$var reg 3 ; state [2:0] $end
$upscope $end
$upscope $end
$scope begin $ivl_for_loop0 $end
$var integer 32 < i [31:0] $end
$upscope $end
$upscope $end
$enddefinitions $end
$comment Show the parameter values. $end
$dumpall
b11 8
b1 7
b0 6
b10 5
b11 0
b1 /
b10 .
b0 -
$end
#0
$dumpvars
bx <
b0 ;
bx :
bx 9
b10 4
b0 3
bx 2
bx 1
b10 ,
x+
x*
x)
b10 (
b10 '
1&
0%
0$
b10 #
b10 "
0!
$end
#2
1+
b0 2
b0 1
b0 9
0*
1)
b0 :
0&
#4
1&
#5
1$
1%
#10
0$
0%
#15
1$
1%
#20
0$
0%
#24
1!
#25
b1 ;
1$
1%
#30
0$
0%
#35
0)
b1 :
1$
1%
#40
0$
0%
#45
b1 3
1*
b10 ;
b0 :
1$
1%
#50
0$
0%
#55
b10 3
b1 2
1)
b1 :
1$
1%
#60
0$
0%
#65
b1 1
b0 2
b1 9
b0 :
1$
1%
#70
0$
0%
#75
b1 2
b1 :
1$
1%
#80
0$
0%
#85
b10 1
b0 2
b10 9
b0 :
1$
1%
#90
0$
0%
#95
b1 2
b1 :
1$
1%
#100
0$
0%
#105
b11 1
b0 2
b11 9
b0 :
1$
1%
#110
0$
0%
#115
b1 2
0)
b1 :
1$
1%
#120
0$
0%
#125
b100 1
0+
b0 2
b100 9
b0 :
1$
1%
#130
0$
0%
#135
b1 2
1)
b1 :
1$
1%
#140
0$
0%
#145
b101 1
1+
b0 2
b101 9
b0 :
1$
1%
#150
0$
0%
#155
b1 2
b1 :
1$
1%
#160
0$
0%
#165
b110 1
b0 2
b110 9
b0 :
1$
1%
#170
0$
0%
#175
b1 2
0)
b1 :
1$
1%
#180
0$
0%
#185
b111 1
0+
b0 2
b111 9
b0 :
1$
1%
#190
0$
0%
#195
b1 2
1)
b1 :
1$
1%
#200
0$
0%
#205
b11 3
b0 2
b11 ;
b0 :
1$
1%
#210
0$
0%
#215
b0 3
1$
1%
#220
0$
0%
#225
b0 1
1$
1%
#230
0$
0%
#235
1$
1%
#240
0$
0%
#245
1$
1%
#250
0$
0%
#255
1$
1%
#260
0$
0%
#265
1$
1%
#270
0$
0%
#275
1$
1%
#280
0$
0%
#285
1$
1%
#290
0$
0%
#295
1$
1%
#300
0$
0%
#305
1$
1%
#310
0$
0%
#315
1$
1%
#320
0$
0%
#325
1$
1%
#330
0$
0%
#335
1$
1%
#340
0$
0%
#345
1$
1%
#350
0$
0%
#355
1$
1%
#360
0$
0%
#365
1$
1%
#370
0$
0%
#375
1$
1%
#380
0$
0%
#385
1$
1%
#390
0$
0%
#395
1$
1%
#400
0$
0%
#405
1$
1%
#410
0$
0%
#415
1$
1%
#420
0$
0%
#424
b1000 <
